test_cli_fake/_init__.py
test_cli_fake/main.py
auth4-1.0.2.dist-info/METADATA
auth4-1.0.2.dist-info/WHEEL
auth4-1.0.2.dist-info/entry_points.txt
auth4-1.0.2.dist-info/RECORD
